mp_time_split/__init__.py
mp_time_split/core.py
mp_time_split/utils/api.py
mp_time_split/utils/data.py
mp_time_split/utils/gen.py
mp_time_split/utils/mp_dummy_time_summary.json
mp_time_split/utils/mp_dummy_time_summary.json.gz
mp_time_split/utils/split.py
mp_time_split-0.2.0.dist-info/LICENSE.txt
mp_time_split-0.2.0.dist-info/METADATA
mp_time_split-0.2.0.dist-info/WHEEL
mp_time_split-0.2.0.dist-info/entry_points.txt
mp_time_split-0.2.0.dist-info/top_level.txt
mp_time_split-0.2.0.dist-info/RECORD
