Metadata-Version: 2.1
Name: mp-time-split
Version: 0.2.0
Summary: Use Materials Project time-splits for generative modeling benchmarking.
Home-page: https://github.com/sparks-baird/mp-time-split
Author: sgbaird
Author-email: sterling.baird@utah.edu
License: MIT
Project-URL: Documentation, https://mp-time-split.readthedocs.io
Project-URL: Source, https://github.com/sparks-baird/mp-time-split
Project-URL: Changelog, https://mp-time-split.readthedocs/en/latest/changelog.html
Project-URL: Tracker, https://github.com/sparks-baird/issues
Project-URL: Conda-Forge, https://anaconda.org/conda-forge/mp_time_split
Project-URL: Download, https://pypi.org/project/mp_time_split/#files
Platform: any
Classifier: Development Status :: 4 - Beta
Classifier: Programming Language :: Python
Requires-Python: >=3.6
License-File: LICENSE.txt
Requires-Dist: scikit-learn
Requires-Dist: pymatgen
Requires-Dist: matminer
Requires-Dist: pybtex
Requires-Dist: typing-extensions
Requires-Dist: importlib-metadata ; python_version < "3.8"
Provides-Extra: api
Requires-Dist: mp-api ; extra == 'api'
Requires-Dist: python-version (>="3.8") ; extra == 'api'
Provides-Extra: pyxtal
Requires-Dist: pyxtal ; extra == 'pyxtal'
Provides-Extra: testing
Requires-Dist: setuptools ; extra == 'testing'
Requires-Dist: pytest ; extra == 'testing'
Requires-Dist: pytest-cov ; extra == 'testing'
Requires-Dist: mp-api ; extra == 'testing'
